birpc/__init__.py
birpc/birpc.py
birpc-0.0.1.dist-info/LICENSE
birpc-0.0.1.dist-info/METADATA
birpc-0.0.1.dist-info/WHEEL
birpc-0.0.1.dist-info/top_level.txt
birpc-0.0.1.dist-info/RECORD
