Metadata-Version: 2.1
Name: birpc
Version: 0.0.1
Summary: Python implementation of the BIRPC js package, a simple RPC over WebSockets
Home-page: https://github.com/igvr/birpc
Author: GPT4
Author-email: pypi.imnu8@simplelogin.com
Classifier: Development Status :: 3 - Alpha
Classifier: Intended Audience :: Developers
Classifier: License :: OSI Approved :: MIT License
Classifier: Programming Language :: Python :: 3
Classifier: Programming Language :: Python :: 3.6
Classifier: Programming Language :: Python :: 3.7
Classifier: Programming Language :: Python :: 3.8
Classifier: Programming Language :: Python :: 3.9
License-File: LICENSE
Requires-Dist: aiohttp
Requires-Dist: rich
